Workbook
Name Aporte: Planilha2!$D$21
Name Rendimento_carteira: Planilha2!$D$15

Sheet Planilha2
B13: CONFIGURAÇÕES
B14: Salario | D14: 4200
B15: Rendimento carteira | D15: 0.01
B16: Sugestão de rendimento (30%) | D16: 1260
B20: INVESTIMENTO MENSAL
B21: quanto investir por mês? | D21: 200
B22: Por quantos anos? | D22: 10
B23: Taxa de rendimento mensal? | D23: 0.01079
B24: Patrimônio acumulado? | D24: =FV(D23,D22*12,D21*-1) -> 48656.843
B25: Dividendos mensais? | D25: =D24*D23 -> 525.00733
B27: Cenários | D27: Dividendo por mês
A28: 2 | B28: Quanto em 2 Anos? | C28: =FV($D$23,$A28*12,$D$21*-1) -> 5445.5255 | D28: =$C28*Rendimento_carteira -> 54.455255
A29: 5 | B29: Quanto em 5 Anos? | C29: =FV($D$23,$A29*12,$D$21*-1) -> 16755.383 | D29: =$C29*Rendimento_carteira -> 167.55383
A30: 10 | B30: Quanto em 10 Anos? | C30: =FV($D$23,$A30*12,$D$21*-1) -> 48656.843 | D30: =$C30*Rendimento_carteira -> 486.56843
A31: 20 | B31: Quanto em 20 Anos? | C31: =FV($D$23,$A31*12,$D$21*-1) -> 225039.68 | D31: =$C31*Rendimento_carteira -> 2250.3968
A32: 30 | B32: Quanto em 30 Anos? | C32: =FV($D$23,$A32*12,$D$21*-1) -> 864433.93 | D32: =$C32*Rendimento_carteira -> 8644.3393
B35: PERFIL | C35: Agressivo
B36: VALOR A SER INVESTIDO POR MÊS | D36: 500
B38: Tipos de FII | C38: Percentual Sugerido | D38: Valores
B39: PAPEL | C39: =VLOOKUP($C$35&"-"&$B39,Planilha1!$A$3:$D$21,4,) -> 0.5 | D39: =C39*Aporte -> 100
B40: TIJOLO | C40: =VLOOKUP($C$35&"-"&$B40,Planilha1!$A$3:$D$21,4,) -> 0.1 | D40: =C40*Aporte -> 20
B41: HÍBRIDOS | C41: =VLOOKUP($C$35&"-"&$B41,Planilha1!$A$3:$D$21,4,) -> 0.05 | D41: =C41*Aporte -> 10
B42: FOF's | C42: =VLOOKUP($C$35&"-"&$B42,Planilha1!$A$3:$D$21,4,) -> 0.05 | D42: =C42*Aporte -> 10
B43: DESENVOLVIMENTO | C43: =VLOOKUP($C$35&"-"&$B43,Planilha1!$A$3:$D$21,4,) -> 0.2 | D43: =C43*Aporte -> 40
B44: HOTELARIAS | C44: =VLOOKUP($C$35&"-"&$B44,Planilha1!$A$3:$D$21,4,) -> 0.1 | D44: =C44*Aporte -> 20
B45: TOTAL | C45: =SUM(C39:C44) -> 1 | D45: =SUM(D39:D44) -> 200

Sheet Planilha1
A3: Chave | B3: Perfil | C3: Tipos de FII | D3: %
A4: Conservador-PAPEL | B4: Conservador | C4: PAPEL | D4: 0.3
A5: Conservador-TIJOLO | B5: Conservador | C5: TIJOLO | D5: 0.5
A6: Conservador-HÍBRIDOS | B6: Conservador | C6: HÍBRIDOS | D6: 0.1
A7: Conservador-FOF's | B7: Conservador | C7: FOF's | D7: 0.1
A8: Conservador-DESENVOLVIMENTO | B8: Conservador | C8: DESENVOLVIMENTO | D8: 0
A9: Conservador-HOTELARIAS | B9: Conservador | C9: HOTELARIAS | D9: 0
A10: Moderado-PAPEL | B10: Moderado | C10: PAPEL | D10: 0.32
A11: Moderado-TIJOLO | B11: Moderado | C11: TIJOLO | D11: 0.35
A12: Moderado-HÍBRIDOS | B12: Moderado | C12: HÍBRIDOS | D12: 0.08
A13: Moderado-FOF's | B13: Moderado | C13: FOF's | D13: 0.05
A14: Moderado-DESENVOLVIMENTO | B14: Moderado | C14: DESENVOLVIMENTO | D14: 0.1
A15: Moderado-HOTELARIAS | B15: Moderado | C15: HOTELARIAS | D15: 0.1
... A21: Agressivo-HOTELARIAS | B21: Agressivo | C21: HOTELARIAS | D21: 0.1
